{
  "data": [
    {
      "img": "http://img01.hua.com/uploadpic/newpic/9010877.jpg_220x240.jpg",
      "title": "新品特价",
      "des":"情有独钟/戴安娜粉玫瑰50枝",
      "price":"￥139"
    },{
      "img": "http://img01.hua.com/uploadpic/newpic/9010734.jpg_220x240.jpg",
      "title": "新品特价",
      "des":"缪斯女神/红玫瑰16枝，",
      "price":"￥279"
    },{
      "img": "http://img01.hua.com/uploadpic/newpic/9010966.jpg_220x240.jpg",
      "title": "新品限量抢购",
      "des":"永生花/To温暖你心/苔藓",
      "price":"￥388"
    },{
      "img": "http://img01.hua.com/uploadpic/newpic/9012142.jpg_220x240.jpg",
      "title": "新品限量抢购",
      "des":"永生花/To温暖你心/苔藓",
      "price":"￥178"
    },
    {
      "img": "http://img01.hua.com/uploadpic/newpic/9012033.jpg_220x240.jpg",
      "title": "新品限量抢购",
      "des":"永生花/To温暖你心/苔藓",
      "price":"￥380"
    },{
      "img": "http://img01.hua.com/uploadpic/newpic/9010668.jpg_220x240.jpg",
      "title": "新品",
      "des":"永生花/To温暖你心/苔藓",
      "price":"￥192"
    },{
      "img": "http://img01.hua.com/uploadpic/newpic/9012125.jpg_220x240.jpg",
      "title": "包装升级款",
      "des":"永生花/To温暖你心/苔藓",
      "price":"￥218"
    },{
      "img": "http://img01.hua.com/uploadpic/newpic/9012112.jpg_220x240.jpg",
      "title": "新品",
      "des":"永生花/To温暖你心/苔藓",
      "price":"￥259"
    },{
      "img": "http://img01.hua.com/uploadpic/newpic/9012079.jpg_220x240.jpg",
      "title": "包装升级款",
      "des":"永生花/To温暖你心/苔藓",
      "price":"￥218"
    },{
      "img": "http://img01.hua.com/uploadpic/newpic/9012062.jpg_220x240.jpg",
      "title": "新品",
      "des":"永生花/To温暖你心/苔藓",
      "price":"￥128"
    },{
      "img": "http://img01.hua.com/uploadpic/newpic/9012089.jpg_220x240.jpg",
      "title": "特价",
      "des":"永生花/To温暖你心/苔藓",
      "price":"￥231"
    },{
      "img": "http://img01.hua.com/uploadpic/newpic/9012141.jpg_220x240.jpg",
      "title": "特价",
      "des":"永生花/To温暖你心/苔藓",
      "price":"￥167"
    }
  ]
}
